correct_hours/__init__.py
correct_hours/__main__.py
correct_hours/processors/__init__.py
correct_hours/processors/myob/__init__.py
correct_hours/processors/myob/timesheet_processor.py
correct_hours/processors/xero/__init__.py
correct_hours/processors/xero/rate_processor.py
correct_hours/processors/xero/timesheet_processor.py
correct_hours/types.py
correct_hours/utils.py
correct_hours/version.py
correct_hours-2.0.1.dist-info/METADATA
correct_hours-2.0.1.dist-info/WHEEL
correct_hours-2.0.1.dist-info/RECORD
